{"text": "Georgia bill that would limit land purchases by Chinese \u2018agents\u2019 passes state House. A bill that would ban any \u201cagent\u201d of China from buying farmland or land near military installations in Georgia passed the state House on Thursday over the objections of Democrats.", "entities": {"Mention": [{"indices": [0, 7], "inst": "http://dbpedia.org/resource/Georgia_(U.S._state)", "dbpInterestingClasses": "dbpedia-owl:PopulatedPlace", "dbpSpecificClasses": "dbpedia-owl:AdministrativeRegion", "confidence": -0.66}, {"indices": [122, 127], "inst": "http://dbpedia.org/resource/China", "dbpInterestingClasses": "dbpedia-owl:PopulatedPlace", "dbpSpecificClasses": "dbpedia-owl:Country", "confidence": 0.66}, {"indices": [188, 195], "inst": "http://dbpedia.org/resource/Georgia_(U.S._state)", "dbpInterestingClasses": "dbpedia-owl:PopulatedPlace", "dbpSpecificClasses": "dbpedia-owl:AdministrativeRegion", "confidence": -0.66}, {"indices": [254, 263], "inst": "http://dbpedia.org/resource/Democratic_Party_(United_States)", "dbpInterestingClasses": "dbpedia-owl:Organisation|dbpedia-owl:Person", "dbpSpecificClasses": "dbpedia-owl:PoliticalParty|dbpedia-owl:Person", "confidence": 0.5100000000000006}]}}