{"text": "\u2018Courageous\u2019 witness stayed with Black transgender woman gunned down in Texas. A courageous and compassionate witness stayed with a Black transgender woman who was fatally shot on a street in Houston on Saturday. Police are now asking for the public\u2019s help identifying and apprehending the victim\u2019s killer.", "entities": {"Mention": [{"indices": [33, 38], "inst": "http://dbpedia.org/resource/Race_and_ethnicity_in_the_United_States_Census", "dbpInterestingClasses": "owl:Thing", "dbpSpecificClasses": "owl:Thing", "confidence": -0.68}, {"indices": [39, 56], "inst": "http://dbpedia.org/resource/Trans_woman", "dbpInterestingClasses": "dbpedia-owl:Person", "dbpSpecificClasses": "dbpedia-owl:Person", "confidence": -0.8116986849697572}, {"indices": [72, 77], "inst": "http://dbpedia.org/resource/Texas", "dbpInterestingClasses": "dbpedia-owl:PopulatedPlace|dbpedia-owl:Person", "dbpSpecificClasses": "dbpedia-owl:AdministrativeRegion|dbpedia-owl:Person", "confidence": -0.58}, {"indices": [130, 137], "inst": "http://dbpedia.org/resource/Andrew_Black_(gambling_entrepreneur)", "dbpInterestingClasses": "dbpedia-owl:Person", "dbpSpecificClasses": "dbpedia-owl:Person", "confidence": -0.63}, {"indices": [138, 155], "inst": "http://dbpedia.org/resource/Trans_woman", "dbpInterestingClasses": "dbpedia-owl:Person", "dbpSpecificClasses": "dbpedia-owl:Person", "confidence": -0.8116986849697572}, {"indices": [192, 199], "inst": "http://dbpedia.org/resource/Houston", "dbpInterestingClasses": "dbpedia-owl:PopulatedPlace", "dbpSpecificClasses": "dbpedia-owl:City|dbpedia-owl:AdministrativeRegion", "confidence": 0.5607692307692308}, {"indices": [213, 219], "inst": "http://dbpedia.org/resource/Police", "dbpInterestingClasses": "dbpedia-owl:Person", "dbpSpecificClasses": "dbpedia-owl:Person|dbpedia-owl:Book", "confidence": -0.73}]}}