{"text": "Shooting at Ramadan celebration in Philadelphia leaves 3 wounded, 5 people arrested. A shooting during a Ramadan event Wednesday afternoon in Philadelphia left three people wounded and five suspects have been arrested, police said.", "entities": {"Mention": [{"indices": [35, 47], "inst": "http://dbpedia.org/resource/Philadelphia", "dbpInterestingClasses": "dbpedia-owl:PopulatedPlace", "dbpSpecificClasses": "dbpedia-owl:City|dbpedia-owl:AdministrativeRegion", "confidence": 0.59}, {"indices": [142, 154], "inst": "http://dbpedia.org/resource/Philadelphia", "dbpInterestingClasses": "dbpedia-owl:PopulatedPlace", "dbpSpecificClasses": "dbpedia-owl:City|dbpedia-owl:AdministrativeRegion", "confidence": 0.59}]}}