{"text": "Ohio warns Democrats that Biden may miss deadline for November ballot. Ohio elections officials told Democratic officials that their nominating convention is too late for President Biden to make the Ohio general election ballot.", "entities": {"Mention": [{"indices": [0, 4], "inst": "http://dbpedia.org/resource/Ohio", "dbpInterestingClasses": "dbpedia-owl:PopulatedPlace", "dbpSpecificClasses": "dbpedia-owl:AdministrativeRegion", "confidence": 0.56}, {"indices": [11, 20], "inst": "http://dbpedia.org/resource/Democratic_Party_(United_States)", "dbpInterestingClasses": "dbpedia-owl:Organisation|dbpedia-owl:Person", "dbpSpecificClasses": "dbpedia-owl:PoliticalParty|dbpedia-owl:Person", "confidence": 0.5100000000000006}, {"indices": [26, 31], "inst": "http://dbpedia.org/resource/Joe_Biden", "dbpInterestingClasses": "dbpedia-owl:Person", "dbpSpecificClasses": "dbpedia-owl:President|dbpedia-owl:VicePresident", "confidence": 0.58}, {"indices": [71, 85], "inst": "http://dbpedia.org/resource/Ohio_elections,_2010", "dbpInterestingClasses": "owl:Thing", "dbpSpecificClasses": "owl:Thing", "confidence": -0.823}, {"indices": [181, 186], "inst": "http://dbpedia.org/resource/Joe_Biden", "dbpInterestingClasses": "dbpedia-owl:Person", "dbpSpecificClasses": "dbpedia-owl:President|dbpedia-owl:VicePresident", "confidence": 0.58}, {"indices": [199, 203], "inst": "http://dbpedia.org/resource/Ohio", "dbpInterestingClasses": "dbpedia-owl:PopulatedPlace", "dbpSpecificClasses": "dbpedia-owl:AdministrativeRegion", "confidence": 0.56}]}}