{"text": "\u2018Dirty Debutantes\u2019 And Other Racist Tropes About LSU Women\u2019s Basketball Team. An L.A. Times writer called the UCLA women\u2019s basketball team \u201cAmerica\u2019s sweethearts.\u201d He referred to LSU players as \u201cbasketball villains\u201d and \u201cdirty debutantes.\u201d", "entities": {"Mention": [{"indices": [36, 42], "inst": "http://dbpedia.org/resource/Trope_(literature)", "dbpInterestingClasses": "owl:Thing", "dbpSpecificClasses": "owl:Thing", "confidence": -0.77}, {"indices": [81, 91], "inst": "http://dbpedia.org/resource/Los_Angeles_Times", "dbpInterestingClasses": "", "dbpSpecificClasses": "dbpedia-owl:Newspaper", "confidence": -0.6286428571428572}, {"indices": [110, 114], "inst": "http://dbpedia.org/resource/University_of_California,_Los_Angeles", "dbpInterestingClasses": "dbpedia-owl:Organisation", "dbpSpecificClasses": "dbpedia-owl:College", "confidence": 0.5607692307692308}, {"indices": [140, 149], "inst": "http://dbpedia.org/resource/United_States", "dbpInterestingClasses": "dbpedia-owl:PopulatedPlace", "dbpSpecificClasses": "dbpedia-owl:Country", "confidence": 0.6633333333333339}, {"indices": [179, 182], "inst": "http://dbpedia.org/resource/Louisiana_State_University", "dbpInterestingClasses": "dbpedia-owl:Organisation", "dbpSpecificClasses": "dbpedia-owl:Location|dbpedia-owl:College", "confidence": 0.5307692307692308}]}}