{"text": "Women\u2019s Sports Hits Tipping Point: FIFA, NWSL And Nebraska Lead Way. The world\u2019s first stadium purpose-built for a women\u2019s sports franchise opened in Kansas City, Missouri on Saturday as the new home of the NWSL\u2019s Kansas City Current.", "entities": {"Mention": [{"indices": [35, 39], "inst": "http://dbpedia.org/resource/FIFA", "dbpInterestingClasses": "dbpedia-owl:Organisation", "dbpSpecificClasses": "dbpedia-owl:SportsLeague|dbpedia-owl:Sport", "confidence": 0.67}, {"indices": [50, 58], "inst": "http://dbpedia.org/resource/Nebraska", "dbpInterestingClasses": "dbpedia-owl:PopulatedPlace", "dbpSpecificClasses": "dbpedia-owl:AdministrativeRegion", "confidence": -0.69}, {"indices": [150, 171], "inst": "http://dbpedia.org/resource/Kansas_City,_Missouri", "dbpInterestingClasses": "dbpedia-owl:PopulatedPlace", "dbpSpecificClasses": "dbpedia-owl:City|dbpedia-owl:AdministrativeRegion", "confidence": 0.5327272727272727}, {"indices": [214, 225], "inst": "http://dbpedia.org/resource/Kansas_City,_Missouri", "dbpInterestingClasses": "dbpedia-owl:PopulatedPlace", "dbpSpecificClasses": "dbpedia-owl:City|dbpedia-owl:AdministrativeRegion", "confidence": 0.5250549450549451}]}}