{"text": "Beyonc\u00e9 Reveals Icon-Studded \u2018Cowboy Carter\u2019 Tracklist With Dolly Parton, Willie Nelson, Linda Martell. In just two days before the drop of her eighth solo album, 'Cowboy Carter,' Beyonce revealed the tracklist of the highliy anticipateed project.", "entities": {"Mention": [{"indices": [0, 7], "inst": "http://dbpedia.org/resource/Beyonc\u00e9", "dbpInterestingClasses": "dbpedia-owl:Person", "dbpSpecificClasses": "dbpedia-owl:Singer", "confidence": 0.59}, {"indices": [16, 20], "inst": "http://dbpedia.org/resource/Icon", "dbpInterestingClasses": "dbpedia-owl:Person", "dbpSpecificClasses": "dbpedia-owl:Person|dbpedia-owl:Book", "confidence": -0.73}, {"indices": [45, 54], "inst": "http://dbpedia.org/resource/Track_(CD)", "dbpInterestingClasses": "owl:Thing", "dbpSpecificClasses": "owl:Thing", "confidence": -0.8240000000000001}, {"indices": [60, 72], "inst": "http://dbpedia.org/resource/Dolly_Parton", "dbpInterestingClasses": "dbpedia-owl:Person", "dbpSpecificClasses": "dbpedia-owl:Singer", "confidence": 0.56}, {"indices": [74, 87], "inst": "http://dbpedia.org/resource/Willie_Nelson", "dbpInterestingClasses": "dbpedia-owl:Person", "dbpSpecificClasses": "dbpedia-owl:Singer", "confidence": 0.61}, {"indices": [89, 102], "inst": "http://dbpedia.org/resource/Linda_Martell", "dbpInterestingClasses": "dbpedia-owl:Person", "dbpSpecificClasses": "dbpedia-owl:Person", "confidence": 0.57}, {"indices": [180, 187], "inst": "http://dbpedia.org/resource/Beyonc\u00e9", "dbpInterestingClasses": "dbpedia-owl:Person", "dbpSpecificClasses": "dbpedia-owl:Singer", "confidence": 0.53}]}}