{"text": "Navy Federal says external review finds \u2018non-race factors\u2019 explained mortgage approval disparities | CNN Business. Navy Federal says external review finds \u2018non-race factors\u2019 explained mortgage approval disparities | CNN Businesscnn.com", "entities": {"Mention": [{"indices": [101, 104], "inst": "http://dbpedia.org/resource/CNN", "dbpInterestingClasses": "dbpedia-owl:Organisation|dbpedia-owl:Person", "dbpSpecificClasses": "dbpedia-owl:TelevisionStation|dbpedia-owl:Person", "confidence": -0.69}, {"indices": [216, 219], "inst": "http://dbpedia.org/resource/CNN", "dbpInterestingClasses": "dbpedia-owl:Organisation|dbpedia-owl:Person", "dbpSpecificClasses": "dbpedia-owl:TelevisionStation|dbpedia-owl:Person", "confidence": -0.69}]}}