{"text": "J.K. Rowling Not Ready to Forgive 'Harry Potter' Stars Daniel Radcliffe, Emma Watson for Vile Transgender Attacks. Author J.K. Rowling appeared to suggest that there may be no forgiveness for \"Harry Potter\" stars Daniel Radcliffe and Emma Watson.\nThe post J.K. Rowling Not Ready to Forgive \u2018Harry Potter\u2019 Stars Daniel Radcliffe, Emma Watson for Vile Transgender Attacks appe\u2026", "entities": {"Mention": [{"indices": [0, 12], "inst": "http://dbpedia.org/resource/J._K._Rowling", "dbpInterestingClasses": "dbpedia-owl:Person", "dbpSpecificClasses": "dbpedia-owl:Writer", "confidence": 0.8075}, {"indices": [35, 47], "inst": "http://dbpedia.org/resource/Harry_Potter", "dbpInterestingClasses": "dbpedia-owl:Person", "dbpSpecificClasses": "dbpedia-owl:Book|dbpedia-owl:Person", "confidence": -0.69}, {"indices": [55, 71], "inst": "http://dbpedia.org/resource/Daniel_Radcliffe", "dbpInterestingClasses": "dbpedia-owl:Person", "dbpSpecificClasses": "dbpedia-owl:Actor", "confidence": 0.82}, {"indices": [73, 84], "inst": "http://dbpedia.org/resource/Emma_Watson", "dbpInterestingClasses": "dbpedia-owl:Person", "dbpSpecificClasses": "dbpedia-owl:Actor", "confidence": 0.82}, {"indices": [94, 105], "inst": "http://dbpedia.org/resource/Transgender", "dbpInterestingClasses": "dbpedia-owl:Person", "dbpSpecificClasses": "dbpedia-owl:Disease|dbpedia-owl:Person", "confidence": -0.5966666666666667}, {"indices": [122, 134], "inst": "http://dbpedia.org/resource/J._K._Rowling", "dbpInterestingClasses": "dbpedia-owl:Person", "dbpSpecificClasses": "dbpedia-owl:Writer", "confidence": 0.8075}, {"indices": [193, 205], "inst": "http://dbpedia.org/resource/Harry_Potter", "dbpInterestingClasses": "dbpedia-owl:Person", "dbpSpecificClasses": "dbpedia-owl:Book|dbpedia-owl:Person", "confidence": -0.69}, {"indices": [213, 229], "inst": "http://dbpedia.org/resource/Daniel_Radcliffe", "dbpInterestingClasses": "dbpedia-owl:Person", "dbpSpecificClasses": "dbpedia-owl:Actor", "confidence": 0.82}, {"indices": [234, 245], "inst": "http://dbpedia.org/resource/Emma_Watson", "dbpInterestingClasses": "dbpedia-owl:Person", "dbpSpecificClasses": "dbpedia-owl:Actor", "confidence": 0.82}, {"indices": [256, 268], "inst": "http://dbpedia.org/resource/J._K._Rowling", "dbpInterestingClasses": "dbpedia-owl:Person", "dbpSpecificClasses": "dbpedia-owl:Writer", "confidence": 0.8075}, {"indices": [291, 303], "inst": "http://dbpedia.org/resource/Harry_Potter", "dbpInterestingClasses": "dbpedia-owl:Person", "dbpSpecificClasses": "dbpedia-owl:Book|dbpedia-owl:Person", "confidence": -0.69}, {"indices": [311, 327], "inst": "http://dbpedia.org/resource/Daniel_Radcliffe", "dbpInterestingClasses": "dbpedia-owl:Person", "dbpSpecificClasses": "dbpedia-owl:Actor", "confidence": 0.82}, {"indices": [329, 340], "inst": "http://dbpedia.org/resource/Emma_Watson", "dbpInterestingClasses": "dbpedia-owl:Person", "dbpSpecificClasses": "dbpedia-owl:Actor", "confidence": 0.82}, {"indices": [350, 361], "inst": "http://dbpedia.org/resource/Transgender", "dbpInterestingClasses": "dbpedia-owl:Person", "dbpSpecificClasses": "dbpedia-owl:Disease|dbpedia-owl:Person", "confidence": -0.5966666666666667}]}}