{"text": "Bill Ackman Strikes Back. Bill Ackman\u2019s fight against Harvard has made him the public face of a billionaire class anxious it no longer rules the worl", "entities": {"Mention": [{"indices": [0, 11], "inst": "http://dbpedia.org/resource/Bill_Ackman", "dbpInterestingClasses": "dbpedia-owl:Person", "dbpSpecificClasses": "dbpedia-owl:Person", "confidence": 0.568}, {"indices": [12, 19], "inst": "http://dbpedia.org/resource/Strike_action", "dbpInterestingClasses": "owl:Thing", "dbpSpecificClasses": "owl:Thing", "confidence": -0.81}, {"indices": [26, 37], "inst": "http://dbpedia.org/resource/Bill_Ackman", "dbpInterestingClasses": "dbpedia-owl:Person", "dbpSpecificClasses": "dbpedia-owl:Person", "confidence": 0.795}, {"indices": [54, 61], "inst": "http://dbpedia.org/resource/Harvard_University", "dbpInterestingClasses": "dbpedia-owl:Organisation", "dbpSpecificClasses": "dbpedia-owl:College", "confidence": 0.5507692307692308}]}}