{"text": "In latest move, Russia adds \u2018LGBT movement\u2019 to official list of extremists and terrorists. Russia has added what it calls the \u201cLGBT movement\u201d to a list of extremist and terrorist organizations, state media said on Friday.", "entities": {"Mention": [{"indices": [16, 22], "inst": "http://dbpedia.org/resource/Russia", "dbpInterestingClasses": "dbpedia-owl:PopulatedPlace", "dbpSpecificClasses": "dbpedia-owl:Country", "confidence": 0.68}, {"indices": [91, 97], "inst": "http://dbpedia.org/resource/Russia", "dbpInterestingClasses": "dbpedia-owl:PopulatedPlace", "dbpSpecificClasses": "dbpedia-owl:Country", "confidence": 0.68}]}}