{"text": "DeSantis and Disney settle lawsuit sparked by Florida governor's 'Don't Say Gay' law. Allies of Gov. Ron DeSantis and Disney reached a settlement agreement Wednesday in a state court fight over how Walt Disney World is developed in the future following the takeover of the theme park resort's government by the Florida governor.", "entities": {"Mention": [{"indices": [13, 19], "inst": "http://dbpedia.org/resource/The_Walt_Disney_Company", "dbpInterestingClasses": "dbpedia-owl:Organisation", "dbpSpecificClasses": "dbpedia-owl:Organisation", "confidence": 0.57}, {"indices": [46, 62], "inst": "http://dbpedia.org/resource/Governor", "dbpInterestingClasses": "", "dbpSpecificClasses": "dbpedia-owl:Book", "confidence": -0.6763095238095238}, {"indices": [101, 113], "inst": "http://dbpedia.org/resource/Ron_DeSantis", "dbpInterestingClasses": "dbpedia-owl:Person", "dbpSpecificClasses": "dbpedia-owl:Politician", "confidence": 0.8975}, {"indices": [118, 124], "inst": "http://dbpedia.org/resource/The_Walt_Disney_Company", "dbpInterestingClasses": "dbpedia-owl:Organisation", "dbpSpecificClasses": "dbpedia-owl:Organisation", "confidence": 0.57}, {"indices": [198, 215], "inst": "http://dbpedia.org/resource/Walt_Disney_World", "dbpInterestingClasses": "dbpedia-owl:Organisation|dbpedia-owl:Person", "dbpSpecificClasses": "dbpedia-owl:Location|dbpedia-owl:Organisation|dbpedia-owl:Person", "confidence": 0.5510482036760903}, {"indices": [273, 283], "inst": "http://dbpedia.org/resource/Amusement_park", "dbpInterestingClasses": "dbpedia-owl:Person", "dbpSpecificClasses": "dbpedia-owl:Person", "confidence": -0.56}, {"indices": [311, 327], "inst": "http://dbpedia.org/resource/Governor", "dbpInterestingClasses": "", "dbpSpecificClasses": "dbpedia-owl:Book", "confidence": -0.6763095238095238}]}}