{"text": "Two recent case of violence showcase the realities LGBTQ people face. NPR's Scott Detrow speaks with Kris Tassone from the National Center For Transgender Equality about how two recent cases of violence against trans people illustrate the realities LGBTQ people face.", "entities": {"Mention": [{"indices": [123, 163], "inst": "http://dbpedia.org/resource/National_Center_for_Transgender_Equality", "dbpInterestingClasses": "dbpedia-owl:Organisation", "dbpSpecificClasses": "dbpedia-owl:Non-ProfitOrganisation", "confidence": 0.8991666666666667}]}}