{"text": "Grindr Gets First Buy Rating as Cowen Sees Growth Outpacing Tinder Owner. (Bloomberg) -- Grindr Inc.\u2019s focus on the LGBTQ+ community promises faster revenue growth than the dating app industry titans, Match Group Inc. and Bumble...", "entities": {"Mention": [{"indices": [0, 6], "inst": "http://dbpedia.org/resource/Grindr", "dbpInterestingClasses": "", "dbpSpecificClasses": "dbpedia-owl:Software", "confidence": -0.5107575757575757}, {"indices": [60, 66], "inst": "http://dbpedia.org/resource/Tinder", "dbpInterestingClasses": "owl:Thing", "dbpSpecificClasses": "owl:Thing", "confidence": -0.86}, {"indices": [75, 84], "inst": "http://dbpedia.org/resource/Bloomberg_L.P.", "dbpInterestingClasses": "dbpedia-owl:Organisation", "dbpSpecificClasses": "dbpedia-owl:Bank", "confidence": -0.8}, {"indices": [89, 95], "inst": "http://dbpedia.org/resource/Grindr", "dbpInterestingClasses": "", "dbpSpecificClasses": "dbpedia-owl:Software", "confidence": -0.7157575757575758}, {"indices": [96, 99], "inst": "http://dbpedia.org/resource/Indian_National_Congress", "dbpInterestingClasses": "dbpedia-owl:Organisation", "dbpSpecificClasses": "dbpedia-owl:PoliticalParty", "confidence": -0.5539999999999999}, {"indices": [116, 132], "inst": "http://dbpedia.org/resource/LGBT", "dbpInterestingClasses": "dbpedia-owl:Person", "dbpSpecificClasses": "dbpedia-owl:Person", "confidence": -0.5399999999999998}, {"indices": [213, 216], "inst": "http://dbpedia.org/resource/Indian_National_Congress", "dbpInterestingClasses": "dbpedia-owl:Organisation", "dbpSpecificClasses": "dbpedia-owl:PoliticalParty", "confidence": -0.5539999999999999}]}}