{"text": "Uganda\u2019s most prominent LGBTQ activist says newly upheld anti-gay law will prompt violence. Uganda\u2019s most prominent LGBTQ activist condemned a constitutional court\u2019s decision to uphold an anti-gay law that permits the death penalty in certain cases.", "entities": {"Mention": [{"indices": [0, 8], "inst": "http://dbpedia.org/resource/Uganda", "dbpInterestingClasses": "dbpedia-owl:PopulatedPlace", "dbpSpecificClasses": "dbpedia-owl:Country", "confidence": 0.5715238095238095}, {"indices": [92, 100], "inst": "http://dbpedia.org/resource/Uganda", "dbpInterestingClasses": "dbpedia-owl:PopulatedPlace", "dbpSpecificClasses": "dbpedia-owl:Country", "confidence": 0.5715238095238095}, {"indices": [218, 231], "inst": "http://dbpedia.org/resource/Capital_punishment", "dbpInterestingClasses": "dbpedia-owl:Person", "dbpSpecificClasses": "dbpedia-owl:Person", "confidence": -0.555}]}}